ikpykit/__init__.py
ikpykit/_version.py
ikpykit/anomaly/__init__.py
ikpykit/anomaly/_idkd.py
ikpykit/anomaly/_iforest.py
ikpykit/anomaly/_inne.py
ikpykit/anomaly/tests/__init__.py
ikpykit/anomaly/tests/test_idkd.py
ikpykit/anomaly/tests/test_inne.py
ikpykit/cluster/__init__.py
ikpykit/cluster/_idkc.py
ikpykit/cluster/_ikahc.py
ikpykit/cluster/_kcluster.py
ikpykit/cluster/_pskc.py
ikpykit/cluster/_utils.py
ikpykit/cluster/tests/__init__.py
ikpykit/cluster/tests/test_idkc.py
ikpykit/cluster/tests/test_ikahc.py
ikpykit/cluster/tests/test_pskc.py
ikpykit/graph/__init__.py
ikpykit/graph/_ikgod.py
ikpykit/graph/_isographkernel.py
ikpykit/graph/utils.py
ikpykit/graph/tests/test_ikgod.py
ikpykit/graph/tests/test_isographkernel.py
ikpykit/group/__init__.py
ikpykit/group/utils.py
ikpykit/group/anomaly/__init__.py
ikpykit/group/anomaly/_ikgad.py
ikpykit/group/tests/test_Ikgad.py
ikpykit/kernel/__init__.py
ikpykit/kernel/_ik_anne.py
ikpykit/kernel/_ik_iforest.py
ikpykit/kernel/_ik_inne.py
ikpykit/kernel/_isodiskernel.py
ikpykit/kernel/_isokernel.py
ikpykit/kernel/tests/__init__.py
ikpykit/kernel/tests/test_isodiskernel.py
ikpykit/kernel/tests/test_isokernel.py
ikpykit/stream/__init__.py
ikpykit/stream/changedetect/__init__.py
ikpykit/stream/changedetect/_icid.py
ikpykit/stream/cluster/__init__.py
ikpykit/stream/cluster/_inode.py
ikpykit/stream/cluster/_streakhc.py
ikpykit/stream/cluster/utils/Graphviz.py
ikpykit/stream/cluster/utils/__init__.py
ikpykit/stream/cluster/utils/deltasep_utils.py
ikpykit/stream/cluster/utils/dendrogram_purity.py
ikpykit/stream/cluster/utils/dendrogram_purity_pool.py
ikpykit/stream/cluster/utils/file_utils.py
ikpykit/stream/cluster/utils/logger.py
ikpykit/stream/cluster/utils/serialize_trees.py
ikpykit/stream/tests/test_icid.py
ikpykit/stream/tests/test_streakhc.py
ikpykit/timeseries/__init__.py
ikpykit/timeseries/anomaly/__init__.py
ikpykit/timeseries/anomaly/_iktod.py
ikpykit/timeseries/tests/test_iktod.py
ikpykit/trajectory/__init__.py
ikpykit-0.2.dist-info/LICENSE
ikpykit-0.2.dist-info/METADATA
ikpykit-0.2.dist-info/WHEEL
ikpykit-0.2.dist-info/top_level.txt
ikpykit-0.2.dist-info/RECORD
