Metadata-Version: 2.2
Name: ikpykit
Version: 0.2
Summary: Isolation Kernel Toolkit in Python.
Author-email: Xin Han <xhan197@outlook.com>, Yixiao Ma <mayx@lamda.nju.edu.cn>, Ye Zhu <ye.zhu@ieee.org>, Kaiming Ting <tingkm@nju.edu.cn>
License: ikpykit (c) by Xin Han
Project-URL: Homepage, https://isolationkernel.github.io/ikpykit/
Project-URL: Repository, https://github.com/IsolationKernel/ikpykit
Project-URL: Documentation, https://isolationkernel.github.io/ikpykit/
Project-URL: Release Notes, https://isolationkernel.github.io/ikpykit/latest/releases/releases
Keywords: data-science,machine-learning,data-mining,anomaly detection,scikit-learn,cluster,graph embedding,isolation kernel
Classifier: Operating System :: MacOS
Classifier: Operating System :: Microsoft :: Windows
Classifier: Operating System :: POSIX
Classifier: Operating System :: Unix
Classifier: Programming Language :: Python
Classifier: Programming Language :: Python :: 3
Classifier: Programming Language :: Python :: 3.9
Classifier: Programming Language :: Python :: 3.10
Classifier: Programming Language :: Python :: 3.11
Classifier: Programming Language :: Python :: 3.12
Classifier: License :: OSI Approved :: BSD License
Requires-Python: >=3.9
License-File: LICENSE
Requires-Dist: scikit-learn>=1.2
Requires-Dist: pandas>=1.5
Requires-Dist: numpy<=1.22
Requires-Dist: numba>=0.54
Requires-Dist: tqdm>=4.62.3
